intake_nexgddp/__init__.py
intake_nexgddp/catalog.py
intake_nexgddp/config_loader.py
intake_nexgddp/resources/visus.config
intake_nexgddp-1.0.5.dist-info/licenses/LICENSE
intake_nexgddp-1.0.5.dist-info/METADATA
intake_nexgddp-1.0.5.dist-info/WHEEL
intake_nexgddp-1.0.5.dist-info/entry_points.txt
intake_nexgddp-1.0.5.dist-info/top_level.txt
intake_nexgddp-1.0.5.dist-info/RECORD
