Metadata-Version: 2.4
Name: intake-nexgddp
Version: 1.0.5
Summary: Intake plugin for NEX-GDDP-CMIP6 via OpenVisus
Author: Aashish Panta
License-File: LICENSE
Requires-Dist: intake
Requires-Dist: xarray
Requires-Dist: numpy
Requires-Dist: openvisus
Dynamic: author
Dynamic: license-file
Dynamic: requires-dist
Dynamic: summary
